{
  "lastUpdated": "2026-07-01T11:37:24.482Z",
  "totalVideos": 200,
  "videos": [
    {
      "videoId": "gHHan3BEg_8",
      "title": "NDPs Changing the whiskey game",
      "channel": "Angry Mac Whiskey Rants ",
      "thumbnail": "https://i.ytimg.com/vi/gHHan3BEg_8/mqdefault.jpg",
      "publishedAt": "2026-07-01T11:35:01Z",
      "categories": [
        "Distilleries"
      ],
      "regions": [],
      "beverageType": "spirits"
    },
    {
      "videoId": "gPPkGCgPUSI",
      "title": "Wine of Air, Earth, and Both: Exploring Musigny #shorts",
      "channel": "LJK Wine ",
      "thumbnail": "https://i.ytimg.com/vi/gPPkGCgPUSI/mqdefault.jpg",
      "publishedAt": "2026-07-01T11:34:23Z",
      "categories": [
        "Tasting & Sommelier",
        "Wines by Region"
      ],
      "regions": [],
      "beverageType": "wine"
    },
    {
      "videoId": "AHDIKYwH8Rc",
      "title": "Labels Off. Which Rye Wins?",
      "channel": "Mash2Glass Discoveries",
      "thumbnail": "https://i.ytimg.com/vi/AHDIKYwH8Rc/mqdefault.jpg",
      "publishedAt": "2026-07-01T11:30:12Z",
      "categories": [
        "Whiskey"
      ],
      "regions": [],
      "beverageType": "spirits"
    },
    {
      "videoId": "GmoqGIojasg",
      "title": "Watch SQUEEZE master Cheese Tincture Herb Fruit Wine Manual Press on Amazon Live",
      "channel": "Tariq Islam",
      "thumbnail": "https://i.ytimg.com/vi/GmoqGIojasg/mqdefault.jpg",
      "publishedAt": "2026-07-01T11:25:31Z",
      "categories": [
        "Wine & Food"
      ],
      "regions": [],
      "beverageType": "wine"
    },
    {
      "videoId": "QJe52cb1D18",
      "title": "#staysmokeytv #podcast #shorts #funny #kentucky #bourbon #bourbontrail #tour #distillery #whiskey",
      "channel": "Stay Smokey TV",
      "thumbnail": "https://i.ytimg.com/vi/QJe52cb1D18/mqdefault.jpg",
      "publishedAt": "2026-07-01T11:20:14Z",
      "categories": [
        "Distilleries"
      ],
      "regions": [
        "Kentucky"
      ],
      "beverageType": "spirits"
    },
    {
      "videoId": "0tcygvsnOYk",
      "title": "Is AI killing Innovation in F&amp;B? #innovation  #ai  #cocktails",
      "channel": "Kompany Hospitality",
      "thumbnail": "https://i.ytimg.com/vi/0tcygvsnOYk/mqdefault.jpg",
      "publishedAt": "2026-07-01T11:19:39Z",
      "categories": [
        "Cocktails & Mixology"
      ],
      "regions": [],
      "beverageType": "spirits"
    },
    {
      "videoId": "PPo7520e0MI",
      "title": "O melhor presente pra quem ama whisky",
      "channel": "Jornada do Whisky",
      "thumbnail": "https://i.ytimg.com/vi/PPo7520e0MI/mqdefault.jpg",
      "publishedAt": "2026-07-01T11:00:33Z",
      "categories": [
        "Whiskey"
      ],
      "regions": [],
      "beverageType": "spirits"
    },
    {
      "videoId": "aV2H-1bQGXs",
      "title": "Wine Estate from Above - Cellar, Vines and Mountain | Cape Winelands 4K",
      "channel": "Alex Sytnik",
      "thumbnail": "https://i.ytimg.com/vi/aV2H-1bQGXs/mqdefault.jpg",
      "publishedAt": "2026-07-01T11:00:30Z",
      "categories": [
        "Wine Collecting & Investment"
      ],
      "regions": [],
      "beverageType": "wine"
    },
    {
      "videoId": "HnV80cZ4Q8o",
      "title": "I&#39;m Not a Wine Drinker... But I Tried a Wine Tasting in France",
      "channel": "One By Land Two By Sea Adventures",
      "thumbnail": "https://i.ytimg.com/vi/HnV80cZ4Q8o/mqdefault.jpg",
      "publishedAt": "2026-07-01T11:00:23Z",
      "categories": [
        "Wines by Region"
      ],
      "regions": [
        "France"
      ],
      "beverageType": "wine"
    },
    {
      "videoId": "rc5JKnWLUd8",
      "title": "We’re changing the game with our new street food and wine pairing experience!",
      "channel": "Our Beijing",
      "thumbnail": "https://i.ytimg.com/vi/rc5JKnWLUd8/mqdefault.jpg",
      "publishedAt": "2026-07-01T11:00:16Z",
      "categories": [
        "Tasting & Sommelier",
        "Wine & Food"
      ],
      "regions": [],
      "beverageType": "wine"
    },
    {
      "videoId": "zcZYG6cok3M",
      "title": "La Sommelière CLASSIC connected ageing wine cellars",
      "channel": "La Sommelière France",
      "thumbnail": "https://i.ytimg.com/vi/zcZYG6cok3M/mqdefault.jpg",
      "publishedAt": "2026-07-01T10:57:07Z",
      "categories": [
        "Wine Collecting & Investment"
      ],
      "regions": [
        "France"
      ],
      "beverageType": "wine"
    },
    {
      "videoId": "5Ss7rV0laLI",
      "title": "Claire Naudin e il miglior Aligotè al mondo 🥂😱👀",
      "channel": "Tellmewine",
      "thumbnail": "https://i.ytimg.com/vi/5Ss7rV0laLI/mqdefault.jpg",
      "publishedAt": "2026-07-01T10:44:54Z",
      "categories": [
        "Tasting & Sommelier"
      ],
      "regions": [],
      "beverageType": "wine"
    },
    {
      "videoId": "pELstYkP9pE",
      "title": "🇮🇹 Scared to Order Wine? 🍷 Italian A1-A2 Phrases That Work",
      "channel": "Say ITALY",
      "thumbnail": "https://i.ytimg.com/vi/pELstYkP9pE/mqdefault.jpg",
      "publishedAt": "2026-07-01T10:42:47Z",
      "categories": [
        "Wines by Region",
        "Wine & Food"
      ],
      "regions": [],
      "beverageType": "wine"
    },
    {
      "videoId": "HfFH5QQGrh0",
      "title": "Çekerek&#39;te Akıllı Bağcılık: Telli Terbiye Sistemiyle Çiftin Başarı Hikayesi",
      "channel": "Yozgat FM & Yozgat TV",
      "thumbnail": "https://i.ytimg.com/vi/HfFH5QQGrh0/mqdefault.jpg",
      "publishedAt": "2026-07-01T10:32:48Z",
      "categories": [
        "Winemaking & Viticulture"
      ],
      "regions": [],
      "beverageType": "wine"
    },
    {
      "videoId": "PeOmb2dRnIE",
      "title": "Historic Wine Cellar",
      "channel": "Swartland Film Collective",
      "thumbnail": "https://i.ytimg.com/vi/PeOmb2dRnIE/mqdefault.jpg",
      "publishedAt": "2026-07-01T10:25:58Z",
      "categories": [
        "Wine Collecting & Investment"
      ],
      "regions": [],
      "beverageType": "wine"
    },
    {
      "videoId": "pJc5fo4kgWg",
      "title": "Precision viticulture RTS system #winestyle #vine",
      "channel": "Wine Style",
      "thumbnail": "https://i.ytimg.com/vi/pJc5fo4kgWg/mqdefault.jpg",
      "publishedAt": "2026-07-01T10:17:10Z",
      "categories": [
        "Winemaking & Viticulture"
      ],
      "regions": [],
      "beverageType": "wine"
    },
    {
      "videoId": "Ix3BhtzG750",
      "title": ". Italy 🇮🇹 on Wine 🍷 enjoy",
      "channel": "bhattajayOfficial🇵🇹",
      "thumbnail": "https://i.ytimg.com/vi/Ix3BhtzG750/mqdefault.jpg",
      "publishedAt": "2026-07-01T10:14:27Z",
      "categories": [
        "Wines by Region"
      ],
      "regions": [],
      "beverageType": "wine"
    },
    {
      "videoId": "JMMiXyRw9BM",
      "title": "S6E5: Chardonnay",
      "channel": "Wines We Drink",
      "thumbnail": "https://i.ytimg.com/vi/JMMiXyRw9BM/mqdefault.jpg",
      "publishedAt": "2026-07-01T10:10:43Z",
      "categories": [
        "Grape Varieties"
      ],
      "regions": [],
      "beverageType": "wine"
    },
    {
      "videoId": "Po544NkP49s",
      "title": "Ilocos Norte From Gold Trade to Sugarcane Wine Wars 🍷🏰",
      "channel": "History Of ???",
      "thumbnail": "https://i.ytimg.com/vi/Po544NkP49s/mqdefault.jpg",
      "publishedAt": "2026-07-01T10:06:46Z",
      "categories": [
        "Business & Trade"
      ],
      "regions": [],
      "beverageType": "wine"
    },
    {
      "videoId": "3uK0EmzqScc",
      "title": "Australia Red Wine Lindeman&#39;s Cawarra Cabernet Merlot 2025",
      "channel": "Green Tea Bar",
      "thumbnail": "https://i.ytimg.com/vi/3uK0EmzqScc/mqdefault.jpg",
      "publishedAt": "2026-07-01T10:06:36Z",
      "categories": [
        "Grape Varieties"
      ],
      "regions": [],
      "beverageType": "wine"
    },
    {
      "videoId": "Ij0knknx-yQ",
      "title": "Episode 33 - Oregon Hill Winery",
      "channel": "Wine Time PA",
      "thumbnail": "https://i.ytimg.com/vi/Ij0knknx-yQ/mqdefault.jpg",
      "publishedAt": "2026-07-01T10:00:30Z",
      "categories": [
        "Wineries"
      ],
      "regions": [],
      "beverageType": "wine"
    },
    {
      "videoId": "WtFSrjrUu5c",
      "title": "Joe Brett’s Ice Cream: Coconut Rum, Chocolate/Vanilla Bourbon/Butter Pecan Bourbon, Peach Whiskey",
      "channel": "Tami Dunn",
      "thumbnail": "https://i.ytimg.com/vi/WtFSrjrUu5c/mqdefault.jpg",
      "publishedAt": "2026-07-01T10:00:30Z",
      "categories": [
        "Rum"
      ],
      "regions": [
        "Kentucky"
      ],
      "beverageType": "spirits"
    },
    {
      "videoId": "RgU4pSmzcNI",
      "title": "Afternoon Tea but Make It Wine I The Cellar@LUXE",
      "channel": "The LUXE Ubud, a Boutique Hotel and The Grill",
      "thumbnail": "https://i.ytimg.com/vi/RgU4pSmzcNI/mqdefault.jpg",
      "publishedAt": "2026-07-01T10:00:23Z",
      "categories": [
        "Wine Collecting & Investment"
      ],
      "regions": [],
      "beverageType": "wine"
    },
    {
      "videoId": "-TdJP2Inp8E",
      "title": "Rye Whiskey: The Next Big Trend",
      "channel": "Bourbon Lens",
      "thumbnail": "https://i.ytimg.com/vi/-TdJP2Inp8E/mqdefault.jpg",
      "publishedAt": "2026-07-01T10:00:22Z",
      "categories": [
        "Whiskey"
      ],
      "regions": [
        "Kentucky"
      ],
      "beverageType": "spirits"
    },
    {
      "videoId": "veTA-QW1Pcg",
      "title": "Premières impressions : le Balblair 15 ans #scotchwhisky #whisky #whiskyreview #balblair",
      "channel": "Whisky et Cie",
      "thumbnail": "https://i.ytimg.com/vi/veTA-QW1Pcg/mqdefault.jpg",
      "publishedAt": "2026-07-01T10:00:16Z",
      "categories": [
        "Whiskey"
      ],
      "regions": [],
      "beverageType": "spirits"
    },
    {
      "videoId": "t4-fdjsT_js",
      "title": "Visit Wollongong Part 3: Grand Pacific Drive, Bald Hill Lookout, Local Distillery, Pleasant Dinner",
      "channel": "Anthony Rahayel",
      "thumbnail": "https://i.ytimg.com/vi/t4-fdjsT_js/mqdefault.jpg",
      "publishedAt": "2026-07-01T10:00:06.000Z",
      "categories": [
        "Distilleries"
      ],
      "regions": [],
      "beverageType": "spirits"
    },
    {
      "videoId": "1U-G12SMdO8",
      "title": "Wine Cru Wednesday- Beringer Napa Valley Zinfandel 1979! #thewinecru #winecruwednesday #vintagewine",
      "channel": "The Wine Cru",
      "thumbnail": "https://i.ytimg.com/vi/1U-G12SMdO8/mqdefault.jpg",
      "publishedAt": "2026-07-01T10:00:04Z",
      "categories": [
        "Wines by Region"
      ],
      "regions": [
        "California"
      ],
      "beverageType": "wine"
    },
    {
      "videoId": "fx0blNxy8Fg",
      "title": "At My Daughter&#39;s Company Celebration, Her Husband Poured Wine On Me: &#39;You&#39;re Just a Janitor&#39;...",
      "channel": "FATHER'S FINAL REVENGE",
      "thumbnail": "https://i.ytimg.com/vi/fx0blNxy8Fg/mqdefault.jpg",
      "publishedAt": "2026-07-01T10:00:03Z",
      "categories": [
        "Business & Trade"
      ],
      "regions": [],
      "beverageType": "wine"
    },
    {
      "videoId": "FmnO_H6vBUw",
      "title": "Cognac VS armagnac  #pourtoi",
      "channel": "Wine Ax ",
      "thumbnail": "https://i.ytimg.com/vi/FmnO_H6vBUw/mqdefault.jpg",
      "publishedAt": "2026-07-01T09:58:08Z",
      "categories": [
        "Brandy & Cognac"
      ],
      "regions": [
        "France"
      ],
      "beverageType": "spirits"
    },
    {
      "videoId": "Ag3txacJ1eM",
      "title": "Log Kya Kahenge? 😂 35,000 Ft Pe France Wine Ke Sath ✈️🍷 #shorts",
      "channel": "DriverSeatTalk",
      "thumbnail": "https://i.ytimg.com/vi/Ag3txacJ1eM/mqdefault.jpg",
      "publishedAt": "2026-07-01T09:56:16Z",
      "categories": [
        "Wines by Region"
      ],
      "regions": [
        "France"
      ],
      "beverageType": "wine"
    },
    {
      "videoId": "xmGwh3_bdNQ",
      "title": "China Storage Containers Hard Shell Box for Moving Dishes Plate Wine",
      "channel": "Shillpyx",
      "thumbnail": "https://i.ytimg.com/vi/xmGwh3_bdNQ/mqdefault.jpg",
      "publishedAt": "2026-07-01T09:54:47Z",
      "categories": [
        "Emerging Wine Regions"
      ],
      "regions": [],
      "beverageType": "wine"
    },
    {
      "videoId": "uc07HzV5sLw",
      "title": "Why do Michelin restaurants Ignore Spirits?",
      "channel": "The Whisky Jury",
      "thumbnail": "https://i.ytimg.com/vi/uc07HzV5sLw/mqdefault.jpg",
      "publishedAt": "2026-07-01T09:50:35Z",
      "categories": [
        "Wine & Food"
      ],
      "regions": [],
      "beverageType": "wine"
    },
    {
      "videoId": "Atbh5N5DWOY",
      "title": "30 सेकंड में जानिए McDowell&#39;s की कीमत!#McDowells #Whisky #WhiskeyPrice #LiquorPrice #StateWisePrice",
      "channel": "businessupdate",
      "thumbnail": "https://i.ytimg.com/vi/Atbh5N5DWOY/mqdefault.jpg",
      "publishedAt": "2026-07-01T09:48:56Z",
      "categories": [
        "Whiskey"
      ],
      "regions": [],
      "beverageType": "spirits"
    },
    {
      "videoId": "1HwHXeqCE0E",
      "title": "Riesling IGT Venezia Giulia Rivièr della cantina Tiare",
      "channel": "Fabio Magnani",
      "thumbnail": "https://i.ytimg.com/vi/1HwHXeqCE0E/mqdefault.jpg",
      "publishedAt": "2026-07-01T09:35:33Z",
      "categories": [
        "Grape Varieties"
      ],
      "regions": [],
      "beverageType": "wine"
    },
    {
      "videoId": "P37bj0vqZ4Y",
      "title": "Gary Vee on Eliminating Friction: The Wine Business Secret &amp; Jets Memories | Boomer &amp; Gio",
      "channel": "Zero Debt Nation",
      "thumbnail": "https://i.ytimg.com/vi/P37bj0vqZ4Y/mqdefault.jpg",
      "publishedAt": "2026-07-01T09:35:26Z",
      "categories": [
        "Business & Trade"
      ],
      "regions": [],
      "beverageType": "wine"
    },
    {
      "videoId": "_tuuFLoqPls",
      "title": "Wine Bricks During Prohibition#shorts",
      "channel": "taja ttf short",
      "thumbnail": "https://i.ytimg.com/vi/_tuuFLoqPls/mqdefault.jpg",
      "publishedAt": "2026-07-01T09:30:38Z",
      "categories": [
        "Business & Trade"
      ],
      "regions": [],
      "beverageType": "wine"
    },
    {
      "videoId": "UWlTQHL-QJ8",
      "title": "Wine Review: Chateau Fontenil Fronsac 1996 - And A Tribute To Michel Rolland",
      "channel": "David Allen - Master of Wine",
      "thumbnail": "https://i.ytimg.com/vi/UWlTQHL-QJ8/mqdefault.jpg",
      "publishedAt": "2026-07-01T09:30:12Z",
      "categories": [
        "Tasting & Sommelier"
      ],
      "regions": [],
      "beverageType": "wine"
    },
    {
      "videoId": "4_UJhRn7ZJ4",
      "title": "Nachproben 2026 | Weiße Burgundersorten und Cuvées",
      "channel": "weinplus - your plus in wine expertise",
      "thumbnail": "https://i.ytimg.com/vi/4_UJhRn7ZJ4/mqdefault.jpg",
      "publishedAt": "2026-07-01T09:29:33Z",
      "categories": [
        "Wines by Region"
      ],
      "regions": [],
      "beverageType": "wine"
    },
    {
      "videoId": "5bDsfTOg7Ww",
      "title": "Behind the Scenes with Noel Edmonds - The Making of River Haven Wine",
      "channel": "Noel Edmonds",
      "thumbnail": "https://i.ytimg.com/vi/5bDsfTOg7Ww/mqdefault.jpg",
      "publishedAt": "2026-07-01T09:27:11Z",
      "categories": [
        "Winemaking & Viticulture"
      ],
      "regions": [],
      "beverageType": "wine"
    },
    {
      "videoId": "rCGpWj691Y4",
      "title": "The BIGGEST Lie In Cheap Red Wine (What&#39;s Really In Your Glass)",
      "channel": "Cellar Atlas",
      "thumbnail": "https://i.ytimg.com/vi/rCGpWj691Y4/mqdefault.jpg",
      "publishedAt": "2026-07-01T09:22:02Z",
      "categories": [
        "Business & Trade"
      ],
      "regions": [],
      "beverageType": "wine"
    },
    {
      "videoId": "fUS1LDQSB10",
      "title": "POV Bartender | 20 Minutes of Cocktail Making 🍸",
      "channel": "ChrisTender",
      "thumbnail": "https://i.ytimg.com/vi/fUS1LDQSB10/mqdefault.jpg",
      "publishedAt": "2026-07-01T09:19:33Z",
      "categories": [
        "Cocktails & Mixology"
      ],
      "regions": [],
      "beverageType": "spirits"
    },
    {
      "videoId": "aCahUKk_1Fo",
      "title": "The Person Who Keeps Johnnie Walker Tasting the Same Every Year",
      "channel": "Cocktail Lore",
      "thumbnail": "https://i.ytimg.com/vi/aCahUKk_1Fo/mqdefault.jpg",
      "publishedAt": "2026-07-01T09:07:52Z",
      "categories": [
        "Whiskey"
      ],
      "regions": [
        "Scotland"
      ],
      "beverageType": "spirits"
    },
    {
      "videoId": "37KEov0kqy4",
      "title": "Curated Wine Pairings",
      "channel": "Restaurant Epos Systems | Self order kiosks | UK",
      "thumbnail": "https://i.ytimg.com/vi/37KEov0kqy4/mqdefault.jpg",
      "publishedAt": "2026-07-01T09:05:31Z",
      "categories": [
        "Wine Collecting & Investment"
      ],
      "regions": [],
      "beverageType": "wine"
    },
    {
      "videoId": "dauViaGwyEQ",
      "title": "The true story behind the Judgement of Paris",
      "channel": "Wine Makers Show",
      "thumbnail": "https://i.ytimg.com/vi/dauViaGwyEQ/mqdefault.jpg",
      "publishedAt": "2026-07-01T09:01:23Z",
      "categories": [
        "Wines by Region"
      ],
      "regions": [],
      "beverageType": "wine"
    },
    {
      "videoId": "JBE4EGjNUL8",
      "title": "LOTS Going On! #bourbon #whiskey #review #barrell #cigar",
      "channel": "Bourbon Theory",
      "thumbnail": "https://i.ytimg.com/vi/JBE4EGjNUL8/mqdefault.jpg",
      "publishedAt": "2026-07-01T09:00:31Z",
      "categories": [
        "Whiskey"
      ],
      "regions": [
        "Kentucky"
      ],
      "beverageType": "spirits"
    },
    {
      "videoId": "A_5u740xEPE",
      "title": "The Wines of Northern Italy: Regions, Grapes and Traditions | Ep. 9 S3",
      "channel": "Europass Italian Language School ",
      "thumbnail": "https://i.ytimg.com/vi/A_5u740xEPE/mqdefault.jpg",
      "publishedAt": "2026-07-01T09:00:18Z",
      "categories": [
        "Wines by Region"
      ],
      "regions": [],
      "beverageType": "wine"
    },
    {
      "videoId": "VXdg15inRFw",
      "title": "mengambil saripati buah anggur yang telah dihaluskan untuk dijadikan minuman fermentasi",
      "channel": "Rentetan shorts",
      "thumbnail": "https://i.ytimg.com/vi/VXdg15inRFw/mqdefault.jpg",
      "publishedAt": "2026-07-01T09:00:18Z",
      "categories": [
        "Winemaking & Viticulture"
      ],
      "regions": [],
      "beverageType": "wine"
    },
    {
      "videoId": "Kzz3nZzsNSk",
      "title": "How do you say &quot;a glass of wine&quot; in Chinese?",
      "channel": "Mandarin with Phoebe",
      "thumbnail": "https://i.ytimg.com/vi/Kzz3nZzsNSk/mqdefault.jpg",
      "publishedAt": "2026-07-01T09:00:16Z",
      "categories": [
        "Emerging Wine Regions"
      ],
      "regions": [],
      "beverageType": "wine"
    },
    {
      "videoId": "_3BCzV3eIUk",
      "title": "Inside Southern Glazer’s: How Distribution Really Works",
      "channel": "Business of Drinks",
      "thumbnail": "https://i.ytimg.com/vi/_3BCzV3eIUk/mqdefault.jpg",
      "publishedAt": "2026-07-01T09:00:11Z",
      "categories": [
        "Spirits Business"
      ],
      "regions": [],
      "beverageType": "spirits"
    },
    {
      "videoId": "-pfrJhy_LKI",
      "title": "Bushmills Original 🥃 | 1608 की कहानी, Taste और Full Review 🔥",
      "channel": "Navneet",
      "thumbnail": "https://i.ytimg.com/vi/-pfrJhy_LKI/mqdefault.jpg",
      "publishedAt": "2026-07-01T08:49:30Z",
      "categories": [
        "Whiskey"
      ],
      "regions": [
        "Ireland"
      ],
      "beverageType": "spirits"
    },
    {
      "videoId": "_hxod0PdPAY",
      "title": "Making The Viral Mini Drink! 🍹✨ #shorts #viral #recipe",
      "channel": "Mini Drinks",
      "thumbnail": "https://i.ytimg.com/vi/_hxod0PdPAY/mqdefault.jpg",
      "publishedAt": "2026-07-01T08:47:25Z",
      "categories": [
        "Cocktails & Mixology"
      ],
      "regions": [],
      "beverageType": "spirits"
    },
    {
      "videoId": "fiinY43er1w",
      "title": "अंगूर की खेती........ || GK || GK Questions || AgricultureGK || GKMCQ",
      "channel": "#GK & Education 0007",
      "thumbnail": "https://i.ytimg.com/vi/fiinY43er1w/mqdefault.jpg",
      "publishedAt": "2026-07-01T08:41:20Z",
      "categories": [
        "Winemaking & Viticulture"
      ],
      "regions": [],
      "beverageType": "wine"
    },
    {
      "videoId": "MWCMDZdJNs0",
      "title": "We adds oak stave to wine cube",
      "channel": "Micro Oxygen Aging Barrel",
      "thumbnail": "https://i.ytimg.com/vi/MWCMDZdJNs0/mqdefault.jpg",
      "publishedAt": "2026-07-01T08:36:50Z",
      "categories": [
        "Wines by Region"
      ],
      "regions": [],
      "beverageType": "wine"
    },
    {
      "videoId": "jb4s96aMm1w",
      "title": "Oz Clarke and Tom Surgey Review The Gunyah Mountfitchet Red 2024  #wine #winelover #winetasting",
      "channel": "The Gunyah Vineyard",
      "thumbnail": "https://i.ytimg.com/vi/jb4s96aMm1w/mqdefault.jpg",
      "publishedAt": "2026-07-01T08:20:09Z",
      "categories": [
        "Tasting & Sommelier"
      ],
      "regions": [],
      "beverageType": "wine"
    },
    {
      "videoId": "84ZmOp6-ZE8",
      "title": "Inside  £4,500,000 Georgian Mansion with 3 Acres, Tennis Court &amp; Wine Cellar",
      "channel": "Property Wealth Network",
      "thumbnail": "https://i.ytimg.com/vi/84ZmOp6-ZE8/mqdefault.jpg",
      "publishedAt": "2026-07-01T08:14:18Z",
      "categories": [
        "Wine Collecting & Investment",
        "Emerging Wine Regions"
      ],
      "regions": [],
      "beverageType": "wine"
    },
    {
      "videoId": "WbtNrvLhPYg",
      "title": "July 2026 - &#39;Wine Trips by Bortodoor&#39;",
      "channel": "Kasper Hovmand Christensen",
      "thumbnail": "https://i.ytimg.com/vi/WbtNrvLhPYg/mqdefault.jpg",
      "publishedAt": "2026-07-01T08:12:40Z",
      "categories": [
        "Business & Trade"
      ],
      "regions": [],
      "beverageType": "wine"
    },
    {
      "videoId": "IDgKoeJqYGQ",
      "title": "Tiny Vineyard Workers Save a Collapsing Grape Harvest! 🍇#Shorts #Viral #TinyWorkers #MiniatureWor",
      "channel": "USA Buzz Central",
      "thumbnail": "https://i.ytimg.com/vi/IDgKoeJqYGQ/mqdefault.jpg",
      "publishedAt": "2026-07-01T08:12:14Z",
      "categories": [
        "Winemaking & Viticulture"
      ],
      "regions": [],
      "beverageType": "wine"
    },
    {
      "videoId": "_Gms-hUVF0Q",
      "title": "Master Sommelier Pierre visits Chateau Mihope in Ningxia for the first time.",
      "channel": "Chateau Mihope",
      "thumbnail": "https://i.ytimg.com/vi/_Gms-hUVF0Q/mqdefault.jpg",
      "publishedAt": "2026-07-01T08:09:07Z",
      "categories": [
        "Wineries"
      ],
      "regions": [],
      "beverageType": "wine"
    },
    {
      "videoId": "f5UDG3kO3AQ",
      "title": "A Peaceful Handmade Day: Harvesting Grapes &amp; Making Wine | Ghibli-style ASMR",
      "channel": "Ghibli Handmade ASMR",
      "thumbnail": "https://i.ytimg.com/vi/f5UDG3kO3AQ/mqdefault.jpg",
      "publishedAt": "2026-07-01T08:03:28Z",
      "categories": [
        "Winemaking & Viticulture"
      ],
      "regions": [],
      "beverageType": "wine"
    },
    {
      "videoId": "rsHiQNK7RsU",
      "title": "Ros de Pacs",
      "channel": "Cata y Disfruta",
      "thumbnail": "https://i.ytimg.com/vi/rsHiQNK7RsU/mqdefault.jpg",
      "publishedAt": "2026-07-01T08:00:06Z",
      "categories": [
        "Tasting & Sommelier",
        "Wine Education"
      ],
      "regions": [],
      "beverageType": "wine"
    },
    {
      "videoId": "zFwOtp7NgvQ",
      "title": "Fresh Pink Grapes Harvest 🍇 Nature&#39;s Sweet Beauty#nature #shorts",
      "channel": "QuantumZilo",
      "thumbnail": "https://i.ytimg.com/vi/zFwOtp7NgvQ/mqdefault.jpg",
      "publishedAt": "2026-07-01T07:52:40Z",
      "categories": [
        "Winemaking & Viticulture"
      ],
      "regions": [],
      "beverageType": "wine"
    },
    {
      "videoId": "XKbJ9NMvJ-g",
      "title": "Bartender Cocktail Making",
      "channel": "Professional Mixologist",
      "thumbnail": "https://i.ytimg.com/vi/XKbJ9NMvJ-g/mqdefault.jpg",
      "publishedAt": "2026-07-01T07:28:13Z",
      "categories": [
        "Cocktails & Mixology"
      ],
      "regions": [],
      "beverageType": "spirits"
    },
    {
      "videoId": "uCB7t9IXW2Q",
      "title": "Wine, Roses &amp; Love – Vintage Italian Love Song With Elegant Amalfi Coast Scenery",
      "channel": "RIAN VINTAGE STUDIO",
      "thumbnail": "https://i.ytimg.com/vi/uCB7t9IXW2Q/mqdefault.jpg",
      "publishedAt": "2026-07-01T07:19:25Z",
      "categories": [
        "Wines by Region"
      ],
      "regions": [],
      "beverageType": "wine"
    },
    {
      "videoId": "iSX1KLmdj30",
      "title": "Why Brits Don&#39;t Drink Boxed Wine, When The French Do?",
      "channel": "You, Me & CPG",
      "thumbnail": "https://i.ytimg.com/vi/iSX1KLmdj30/mqdefault.jpg",
      "publishedAt": "2026-07-01T07:00:26Z",
      "categories": [
        "Wines by Region"
      ],
      "regions": [],
      "beverageType": "wine"
    },
    {
      "videoId": "PbqNqXbv_30",
      "title": "Advances in flotation for grape must clarification",
      "channel": "Wine Operations & Supply Chain Management Group",
      "thumbnail": "https://i.ytimg.com/vi/PbqNqXbv_30/mqdefault.jpg",
      "publishedAt": "2026-07-01T07:00:06Z",
      "categories": [
        "Winemaking & Viticulture"
      ],
      "regions": [],
      "beverageType": "wine"
    },
    {
      "videoId": "bqrrvt3hTVY",
      "title": "THE IRISH BUCK COCKTAIL 🥃#yt #ytshorts #asrm #cocktail  #whiskey  #monkeyshoulder #scotch #love",
      "channel": "Mixology gyan ",
      "thumbnail": "https://i.ytimg.com/vi/bqrrvt3hTVY/mqdefault.jpg",
      "publishedAt": "2026-07-01T06:48:01Z",
      "categories": [
        "Whiskey"
      ],
      "regions": [
        "Scotland"
      ],
      "beverageType": "spirits"
    },
    {
      "videoId": "69a8u8D7kFA",
      "title": "LETS GO TO NAPA🧺💭🍇🍷🤍#travelvlog #napa #dayinmylife #napacounty #hotairballoon #californiavlog",
      "channel": "zanthippie macrae",
      "thumbnail": "https://i.ytimg.com/vi/69a8u8D7kFA/mqdefault.jpg",
      "publishedAt": "2026-07-01T06:46:13Z",
      "categories": [
        "Wines by Region"
      ],
      "regions": [],
      "beverageType": "wine"
    },
    {
      "videoId": "zNDl-Y6HJJg",
      "title": "Stay Smokin&#39; - Bourbon in a Pipe  - Ep.23 (Full Stream)",
      "channel": "Cigar Chief",
      "thumbnail": "https://i.ytimg.com/vi/zNDl-Y6HJJg/mqdefault.jpg",
      "publishedAt": "2026-07-01T06:44:18Z",
      "categories": [
        "Whiskey"
      ],
      "regions": [
        "Kentucky"
      ],
      "beverageType": "spirits"
    },
    {
      "videoId": "mSEUF87LAVE",
      "title": "Newair 24 Wine Cooler Refrigerator Large 116 Honest Review 2026",
      "channel": "Techno Gaming",
      "thumbnail": "https://i.ytimg.com/vi/mSEUF87LAVE/mqdefault.jpg",
      "publishedAt": "2026-07-01T06:31:44Z",
      "categories": [
        "Wine Collecting & Investment"
      ],
      "regions": [],
      "beverageType": "wine"
    },
    {
      "videoId": "zMKarHHNWQc",
      "title": "Every unforgettable course deserves the perfect pairing 🦞🥂",
      "channel": "Rottnest Cruises",
      "thumbnail": "https://i.ytimg.com/vi/zMKarHHNWQc/mqdefault.jpg",
      "publishedAt": "2026-07-01T06:30:59Z",
      "categories": [
        "Tasting & Sommelier"
      ],
      "regions": [],
      "beverageType": "wine"
    },
    {
      "videoId": "7GxJUmt0SlM",
      "title": "This Is the Brunello Vintage We&#39;ve Been Waiting For",
      "channel": "Wine Exchange",
      "thumbnail": "https://i.ytimg.com/vi/7GxJUmt0SlM/mqdefault.jpg",
      "publishedAt": "2026-07-01T06:27:37Z",
      "categories": [
        "Wines by Region"
      ],
      "regions": [
        "Italy"
      ],
      "beverageType": "wine"
    },
    {
      "videoId": "UbRMCwawi4Y",
      "title": "Asad Bourbon Lattafa Review | Parfum Arabesc Bărbătesc Inspirat de Azzaro Most Wanted",
      "channel": "Unpuf",
      "thumbnail": "https://i.ytimg.com/vi/UbRMCwawi4Y/mqdefault.jpg",
      "publishedAt": "2026-07-01T06:23:36Z",
      "categories": [
        "Whiskey"
      ],
      "regions": [
        "Kentucky"
      ],
      "beverageType": "spirits"
    },
    {
      "videoId": "cHyIHXF1OA4",
      "title": "Tasting All 10 Four Roses Recipes #whiskyinsv 177",
      "channel": "Whisky in SV",
      "thumbnail": "https://i.ytimg.com/vi/cHyIHXF1OA4/mqdefault.jpg",
      "publishedAt": "2026-07-01T06:11:09Z",
      "categories": [
        "Whiskey"
      ],
      "regions": [
        "Kentucky"
      ],
      "beverageType": "spirits"
    },
    {
      "videoId": "caEQcSXdDO8",
      "title": "￼Benchmark Single Barrel Review",
      "channel": "JJbourbq",
      "thumbnail": "https://i.ytimg.com/vi/caEQcSXdDO8/mqdefault.jpg",
      "publishedAt": "2026-07-01T06:00:28Z",
      "categories": [
        "Whiskey"
      ],
      "regions": [],
      "beverageType": "spirits"
    },
    {
      "videoId": "fVMct1pQijg",
      "title": "🇬🇪 Tbilisi | यूरोप का छिपा हुआ रत्न! 😍  | Complete Travel Guide 2026#sorts #travelguide#world#city",
      "channel": "World City Guide 360",
      "thumbnail": "https://i.ytimg.com/vi/fVMct1pQijg/mqdefault.jpg",
      "publishedAt": "2026-07-01T06:00:14Z",
      "categories": [
        "Emerging Wine Regions"
      ],
      "regions": [],
      "beverageType": "wine"
    },
    {
      "videoId": "eJ26_85br74",
      "title": "wine red✨🍒 #burgundy #fyp #whitemustang",
      "channel": "itx_violet",
      "thumbnail": "https://i.ytimg.com/vi/eJ26_85br74/mqdefault.jpg",
      "publishedAt": "2026-07-01T05:58:57Z",
      "categories": [
        "Wines by Region"
      ],
      "regions": [
        "France"
      ],
      "beverageType": "wine"
    },
    {
      "videoId": "uhgl6x0r6Tw",
      "title": "professor pruning the wine grapes in Montepulciano #italy",
      "channel": "Davide and his Adventure in Tuscany! ",
      "thumbnail": "https://i.ytimg.com/vi/uhgl6x0r6Tw/mqdefault.jpg",
      "publishedAt": "2026-07-01T05:48:24Z",
      "categories": [
        "Wines by Region"
      ],
      "regions": [
        "Italy"
      ],
      "beverageType": "wine"
    },
    {
      "videoId": "vRZ6fw2ShEg",
      "title": "Chinese Dance Sensation Liu Zhimin&#39;s Courtly Performance - Wine Cup Legs",
      "channel": "Ciel",
      "thumbnail": "https://i.ytimg.com/vi/vRZ6fw2ShEg/mqdefault.jpg",
      "publishedAt": "2026-07-01T05:36:32Z",
      "categories": [
        "Emerging Wine Regions"
      ],
      "regions": [],
      "beverageType": "wine"
    },
    {
      "videoId": "pf5MJwW050Q",
      "title": "Why Winemakers Are Giving Up on Ice Wine?",
      "channel": "WineryReport",
      "thumbnail": "https://i.ytimg.com/vi/pf5MJwW050Q/mqdefault.jpg",
      "publishedAt": "2026-07-01T05:35:00Z",
      "categories": [
        "Sustainability & Climate"
      ],
      "regions": [],
      "beverageType": "wine"
    },
    {
      "videoId": "eReJ0OsI1ew",
      "title": "Respect to Everyone Who Makes this dish #viralshots",
      "channel": "Life full Sasi",
      "thumbnail": "https://i.ytimg.com/vi/eReJ0OsI1ew/mqdefault.jpg",
      "publishedAt": "2026-07-01T05:33:57Z",
      "categories": [
        "Cocktails & Mixology"
      ],
      "regions": [],
      "beverageType": "spirits"
    },
    {
      "videoId": "sbhnXmZ33ho",
      "title": "Bí mật Armagnac từ lò chưng cất 1919 #shorts",
      "channel": "DangTau Whisky",
      "thumbnail": "https://i.ytimg.com/vi/sbhnXmZ33ho/mqdefault.jpg",
      "publishedAt": "2026-07-01T05:30:29Z",
      "categories": [
        "Brandy & Cognac"
      ],
      "regions": [
        "France"
      ],
      "beverageType": "spirits"
    },
    {
      "videoId": "_C0zY9YvCLo",
      "title": "Maotai-style baijiu is seeking overseas agents and distributors. #baijiu #liquor #alcohol #fyp",
      "channel": "Huanjiu Baijiu ",
      "thumbnail": "https://i.ytimg.com/vi/_C0zY9YvCLo/mqdefault.jpg",
      "publishedAt": "2026-07-01T05:30:13Z",
      "categories": [
        "Spirits Business"
      ],
      "regions": [],
      "beverageType": "spirits"
    },
    {
      "videoId": "gXPlGMn1kS4",
      "title": "Palm Wine Tapping in Africa 🌴 Fresh Palm Wine Harvest From Start to Finish!",
      "channel": "Anthony the Young tapper.",
      "thumbnail": "https://i.ytimg.com/vi/gXPlGMn1kS4/mqdefault.jpg",
      "publishedAt": "2026-07-01T05:23:40Z",
      "categories": [
        "Winemaking & Viticulture"
      ],
      "regions": [],
      "beverageType": "wine"
    },
    {
      "videoId": "DOVnz2UTzKk",
      "title": "Bas-armagnac de 31 ans du Domaine de Péré, sélectionné brut de fût par Alabat Armagnac.",
      "channel": "Fred Tillac",
      "thumbnail": "https://i.ytimg.com/vi/DOVnz2UTzKk/mqdefault.jpg",
      "publishedAt": "2026-07-01T05:23:24Z",
      "categories": [
        "Brandy & Cognac"
      ],
      "regions": [
        "France"
      ],
      "beverageType": "spirits"
    },
    {
      "videoId": "_rtUGzOVNX8",
      "title": "Heaven I’m heaven 🎶 #sommelier #viajes #wine",
      "channel": "Karina Valero Somm",
      "thumbnail": "https://i.ytimg.com/vi/_rtUGzOVNX8/mqdefault.jpg",
      "publishedAt": "2026-07-01T05:14:39Z",
      "categories": [
        "Tasting & Sommelier"
      ],
      "regions": [],
      "beverageType": "wine"
    },
    {
      "videoId": "LPuVvP7ox-Y",
      "title": "Santa Teresa Gran Reserva Ron Anejo Rum Full Review ",
      "channel": "Mr.Randy's Wine & Spirits",
      "thumbnail": "https://i.ytimg.com/vi/LPuVvP7ox-Y/mqdefault.jpg",
      "publishedAt": "2026-07-01T05:00:34Z",
      "categories": [
        "Rum"
      ],
      "regions": [],
      "beverageType": "spirits"
    },
    {
      "videoId": "ja2nSXop-1Y",
      "title": "POV: Whisky &amp; Coffee First Batch",
      "channel": "Heaps Good Spirits",
      "thumbnail": "https://i.ytimg.com/vi/ja2nSXop-1Y/mqdefault.jpg",
      "publishedAt": "2026-07-01T05:00:24Z",
      "categories": [
        "Whiskey"
      ],
      "regions": [],
      "beverageType": "spirits"
    },
    {
      "videoId": "lvS2d7NbZGo",
      "title": "The Sommelier of Disaster, Sommelier ignores a raging kitchen fire!#focus #deadpan #firefail #comedy",
      "channel": "Break the loop",
      "thumbnail": "https://i.ytimg.com/vi/lvS2d7NbZGo/mqdefault.jpg",
      "publishedAt": "2026-07-01T05:00:06Z",
      "categories": [
        "Tasting & Sommelier"
      ],
      "regions": [],
      "beverageType": "wine"
    },
    {
      "videoId": "q1MurrXaJHg",
      "title": "Bhaiya Teacher&#39;s Highland Cream Reserve🥃#teachers #whisky #daru #shortsfeed #shorts #review",
      "channel": "Bhai Theke Wala",
      "thumbnail": "https://i.ytimg.com/vi/q1MurrXaJHg/mqdefault.jpg",
      "publishedAt": "2026-07-01T04:36:00Z",
      "categories": [
        "Whiskey"
      ],
      "regions": [],
      "beverageType": "spirits"
    },
    {
      "videoId": "yly3CmZqLw0",
      "title": "Boeuf Bourguignon, A taste of French elegance, one spoonful at a time.. #cuisine #france #wine",
      "channel": "Chef AI Guldo",
      "thumbnail": "https://i.ytimg.com/vi/yly3CmZqLw0/mqdefault.jpg",
      "publishedAt": "2026-07-01T04:24:23Z",
      "categories": [
        "Wines by Region"
      ],
      "regions": [
        "France"
      ],
      "beverageType": "wine"
    },
    {
      "videoId": "-aX84Z1_prM",
      "title": "WQV Manual Juicer Press Review - Pros &amp; Cons - WQV 3.2 Gallon Fruit Wine Press",
      "channel": "BakingReview",
      "thumbnail": "https://i.ytimg.com/vi/-aX84Z1_prM/mqdefault.jpg",
      "publishedAt": "2026-07-01T04:08:16Z",
      "categories": [
        "Wine & Food"
      ],
      "regions": [],
      "beverageType": "wine"
    },
    {
      "videoId": "uyMcOwe6yQM",
      "title": "Teacher&#39;s Blended Scotch Whisky",
      "channel": "MCNAIR HOUSE OF AUTHENTIC LIQUOR",
      "thumbnail": "https://i.ytimg.com/vi/uyMcOwe6yQM/mqdefault.jpg",
      "publishedAt": "2026-07-01T04:05:47Z",
      "categories": [
        "Whiskey"
      ],
      "regions": [
        "Scotland"
      ],
      "beverageType": "spirits"
    },
    {
      "videoId": "SvYVhe-n6aw",
      "title": "Hotel Fioroni | Bellagio, Italy | Hotel Review ⭐",
      "channel": "Hotel Scout Italy",
      "thumbnail": "https://i.ytimg.com/vi/SvYVhe-n6aw/mqdefault.jpg",
      "publishedAt": "2026-07-01T04:01:51Z",
      "categories": [
        "Wines by Region"
      ],
      "regions": [],
      "beverageType": "wine"
    },
    {
      "videoId": "epN9Uzkn4iE",
      "title": "A Day at a Vodkow Distillery | Taste Test &amp; Tour",
      "channel": "MikuEla Vlogs",
      "thumbnail": "https://i.ytimg.com/vi/epN9Uzkn4iE/mqdefault.jpg",
      "publishedAt": "2026-07-01T04:00:23Z",
      "categories": [
        "Distilleries"
      ],
      "regions": [],
      "beverageType": "spirits"
    },
    {
      "videoId": "L2UGifcaHHE",
      "title": "Freemark Abbey &amp; the Judgment of Paris: Kristy Melton on the Winery That Changed American Wine",
      "channel": "thewinecoach",
      "thumbnail": "https://i.ytimg.com/vi/L2UGifcaHHE/mqdefault.jpg",
      "publishedAt": "2026-07-01T04:00:18Z",
      "categories": [
        "Wines by Region",
        "Grape Varieties"
      ],
      "regions": [],
      "beverageType": "wine"
    },
    {
      "videoId": "BmF-PTog3sg",
      "title": "🥃 BEST FRIENDS BLIND | Whiskey Edition 🥃Whatch Grabbing ?",
      "channel": "Sip, Savor & Celebrate ",
      "thumbnail": "https://i.ytimg.com/vi/BmF-PTog3sg/mqdefault.jpg",
      "publishedAt": "2026-07-01T04:00:06Z",
      "categories": [
        "Whiskey"
      ],
      "regions": [],
      "beverageType": "spirits"
    },
    {
      "videoId": "mECMOQ0QG50",
      "title": "fresh lime 🍋‍🟩 jaljeera soda 🥤 making #shorts #travel #soda #foodie #drink #fyp",
      "channel": "foodie darshan",
      "thumbnail": "https://i.ytimg.com/vi/mECMOQ0QG50/mqdefault.jpg",
      "publishedAt": "2026-07-01T03:47:20Z",
      "categories": [
        "Cocktails & Mixology"
      ],
      "regions": [],
      "beverageType": "spirits"
    },
    {
      "videoId": "Htiv8797srw",
      "title": "🍶 Hidden Gem Jimo Huangjiu! An Authentic Chinese Rice Wine Worth Trying",
      "channel": "Authentic shaozing ",
      "thumbnail": "https://i.ytimg.com/vi/Htiv8797srw/mqdefault.jpg",
      "publishedAt": "2026-07-01T03:23:25Z",
      "categories": [
        "Emerging Wine Regions"
      ],
      "regions": [],
      "beverageType": "wine"
    },
    {
      "videoId": "kumxFXv7ePM",
      "title": "Old Carter Rye Vs Kentucky Owl Rye!",
      "channel": "Bourbonandmorebourbon",
      "thumbnail": "https://i.ytimg.com/vi/kumxFXv7ePM/mqdefault.jpg",
      "publishedAt": "2026-07-01T03:14:44Z",
      "categories": [
        "Whiskey"
      ],
      "regions": [
        "Kentucky"
      ],
      "beverageType": "spirits"
    },
    {
      "videoId": "KHiPFCoJdN4",
      "title": "film is called &quot;Cheese Burglar&quot; btw 😭",
      "channel": "3400 Records",
      "thumbnail": "https://i.ytimg.com/vi/KHiPFCoJdN4/mqdefault.jpg",
      "publishedAt": "2026-07-01T03:09:18Z",
      "categories": [
        "Wine & Food"
      ],
      "regions": [],
      "beverageType": "wine"
    },
    {
      "videoId": "T5q2IIhoIGY",
      "title": "Seelbach&#39;s Weekly Review LIVE - Week of July 5 - July  11",
      "channel": "Seelbach's",
      "thumbnail": "https://i.ytimg.com/vi/T5q2IIhoIGY/mqdefault.jpg",
      "publishedAt": "2026-07-01T03:04:50Z",
      "categories": [
        "Tasting & Sommelier"
      ],
      "regions": [],
      "beverageType": "wine"
    },
    {
      "videoId": "kC36RDJ0pYQ",
      "title": "Red Wine Soap#organiclifestyle #healthyskin #chemicalfree #trending #healthyliving",
      "channel": "Riyaa Earthcare",
      "thumbnail": "https://i.ytimg.com/vi/kC36RDJ0pYQ/mqdefault.jpg",
      "publishedAt": "2026-07-01T02:58:42Z",
      "categories": [
        "Winemaking & Viticulture",
        "Sustainability & Climate"
      ],
      "regions": [],
      "beverageType": "wine"
    },
    {
      "videoId": "KjgX5vorNCE",
      "title": "A good Rye is what ya need",
      "channel": "SmallTownPours",
      "thumbnail": "https://i.ytimg.com/vi/KjgX5vorNCE/mqdefault.jpg",
      "publishedAt": "2026-07-01T02:55:24Z",
      "categories": [
        "Whiskey"
      ],
      "regions": [],
      "beverageType": "spirits"
    },
    {
      "videoId": "cJXdElmtmjA",
      "title": "Tokara Wine: Tropical Fruit &amp; Herbaceous Notes Explored! #shorts",
      "channel": "Taste This TV Show",
      "thumbnail": "https://i.ytimg.com/vi/cJXdElmtmjA/mqdefault.jpg",
      "publishedAt": "2026-07-01T02:54:34Z",
      "categories": [
        "Tasting & Sommelier"
      ],
      "regions": [],
      "beverageType": "wine"
    },
    {
      "videoId": "eyZjHJc3xMA",
      "title": "Japanese Wines to Drink Now | 4 Sommelier Picks (May 2026)",
      "channel": "Japan Cellar ",
      "thumbnail": "https://i.ytimg.com/vi/eyZjHJc3xMA/mqdefault.jpg",
      "publishedAt": "2026-07-01T02:46:26Z",
      "categories": [
        "Tasting & Sommelier"
      ],
      "regions": [],
      "beverageType": "wine"
    },
    {
      "videoId": "VveNgkCt4Q8",
      "title": "Making 😱The Viral Mini Drink! 🍹✨ #shorts #viral #recipe",
      "channel": "Mini Drinks",
      "thumbnail": "https://i.ytimg.com/vi/VveNgkCt4Q8/mqdefault.jpg",
      "publishedAt": "2026-07-01T02:31:20Z",
      "categories": [
        "Cocktails & Mixology"
      ],
      "regions": [],
      "beverageType": "spirits"
    },
    {
      "videoId": "B_VaMCCjHEU",
      "title": "Nước vải lên men tự làm #cooking #food #monngon #monngonmoingay #amthuc #nauan #anvat #anngon #ngon",
      "channel": "monngontrunghoa888",
      "thumbnail": "https://i.ytimg.com/vi/B_VaMCCjHEU/mqdefault.jpg",
      "publishedAt": "2026-07-01T02:30:08Z",
      "categories": [
        "Winemaking & Viticulture",
        "Wine & Food"
      ],
      "regions": [],
      "beverageType": "wine"
    },
    {
      "videoId": "x837jGYFPmQ",
      "title": "The Duck Who Thinks He&#39;s a Wine Sommelier 🍇🦆 #duck #funnyanimals #sommelier  #cute #funny #viral",
      "channel": "Pet Memes",
      "thumbnail": "https://i.ytimg.com/vi/x837jGYFPmQ/mqdefault.jpg",
      "publishedAt": "2026-07-01T02:27:44Z",
      "categories": [
        "Tasting & Sommelier"
      ],
      "regions": [],
      "beverageType": "wine"
    },
    {
      "videoId": "gfVju3komXQ",
      "title": "Chit Chat Atlanta Tours Nashville  Cultural Tour Experience Uncle Nearest Premium Whiskey Distillery",
      "channel": "Carla Morrison",
      "thumbnail": "https://i.ytimg.com/vi/gfVju3komXQ/mqdefault.jpg",
      "publishedAt": "2026-07-01T02:18:53Z",
      "categories": [
        "Distilleries"
      ],
      "regions": [
        "Tennessee"
      ],
      "beverageType": "spirits"
    },
    {
      "videoId": "2m2jOyYfWEI",
      "title": "Rockburn Amber 2024",
      "channel": "Rockburn Wines Central Otago",
      "thumbnail": "https://i.ytimg.com/vi/2m2jOyYfWEI/mqdefault.jpg",
      "publishedAt": "2026-07-01T02:10:19Z",
      "categories": [
        "Grape Varieties"
      ],
      "regions": [
        "New Zealand"
      ],
      "beverageType": "wine"
    },
    {
      "videoId": "EmjldcbcU4Y",
      "title": "Rye Whiskey Review: 90 Proof vs 100 Proof Showdown #shorts",
      "channel": "MoJo Whiskey Bar",
      "thumbnail": "https://i.ytimg.com/vi/EmjldcbcU4Y/mqdefault.jpg",
      "publishedAt": "2026-07-01T02:02:28Z",
      "categories": [
        "Whiskey"
      ],
      "regions": [],
      "beverageType": "spirits"
    },
    {
      "videoId": "CzrvjjdbCSs",
      "title": "Highland vs Valley Tequila Blind Test… Can You Tell the Difference?",
      "channel": "Tasting Tequila with Brad",
      "thumbnail": "https://i.ytimg.com/vi/CzrvjjdbCSs/mqdefault.jpg",
      "publishedAt": "2026-07-01T02:00:36Z",
      "categories": [
        "Tequila & Mezcal"
      ],
      "regions": [
        "Jalisco"
      ],
      "beverageType": "spirits"
    },
    {
      "videoId": "jY09GrcYYLo",
      "title": "Minden Mill Nevada Straight Bourbon Whiskey | Full Review &amp; Taste Test",
      "channel": "Beardly Bourbon and Spirits",
      "thumbnail": "https://i.ytimg.com/vi/jY09GrcYYLo/mqdefault.jpg",
      "publishedAt": "2026-07-01T02:00:07Z",
      "categories": [
        "Whiskey"
      ],
      "regions": [
        "Kentucky"
      ],
      "beverageType": "spirits"
    },
    {
      "videoId": "Oet-66KSeMg",
      "title": "How To Become A Wine Educator | BBC Journalist to Wine Expert",
      "channel": "How To Become A...",
      "thumbnail": "https://i.ytimg.com/vi/Oet-66KSeMg/mqdefault.jpg",
      "publishedAt": "2026-07-01T01:53:34Z",
      "categories": [
        "Wine Education"
      ],
      "regions": [],
      "beverageType": "wine"
    },
    {
      "videoId": "kmjyGWS2xhI",
      "title": "Highly recommend Rum Cakes Factory So delicious and moist! #cake #review #texasrealestate #texas",
      "channel": "Lidia",
      "thumbnail": "https://i.ytimg.com/vi/kmjyGWS2xhI/mqdefault.jpg",
      "publishedAt": "2026-07-01T01:50:57Z",
      "categories": [
        "Rum"
      ],
      "regions": [],
      "beverageType": "spirits"
    },
    {
      "videoId": "gu8oTubmJDI",
      "title": "Story Behind the Bottle: James E. Pepper 1776 Straight Rye Whiskey",
      "channel": "One Ear Whiskey",
      "thumbnail": "https://i.ytimg.com/vi/gu8oTubmJDI/mqdefault.jpg",
      "publishedAt": "2026-07-01T01:16:12Z",
      "categories": [
        "Whiskey"
      ],
      "regions": [],
      "beverageType": "spirits"
    },
    {
      "videoId": "PEZcAhpMALY",
      "title": "Tasting Notes For Rysak Wine From Czechia",
      "channel": "Stanley's Wet Goods",
      "thumbnail": "https://i.ytimg.com/vi/PEZcAhpMALY/mqdefault.jpg",
      "publishedAt": "2026-07-01T01:11:01Z",
      "categories": [
        "Business & Trade",
        "Tasting & Sommelier",
        "Winemaking & Viticulture"
      ],
      "regions": [],
      "beverageType": "wine"
    },
    {
      "videoId": "qDhRQ8TmC4M",
      "title": "Stagg 26A   Review: Is This $70 Bottle Worth Buying? #shorts",
      "channel": "Old Fashioned Ways++ ",
      "thumbnail": "https://i.ytimg.com/vi/qDhRQ8TmC4M/mqdefault.jpg",
      "publishedAt": "2026-07-01T01:03:59Z",
      "categories": [
        "Whiskey"
      ],
      "regions": [],
      "beverageType": "spirits"
    },
    {
      "videoId": "GT8DYYvsfvs",
      "title": "I Went to a Coffee Tasting… and Now I&#39;m Obsessed ☕🤎",
      "channel": "heilly",
      "thumbnail": "https://i.ytimg.com/vi/GT8DYYvsfvs/mqdefault.jpg",
      "publishedAt": "2026-07-01T01:02:43Z",
      "categories": [
        "Tequila & Mezcal"
      ],
      "regions": [],
      "beverageType": "spirits"
    },
    {
      "videoId": "QsDoyCBHub0",
      "title": "Hot Takes on Wine With Ross Maloof of Maloof Wines",
      "channel": "Stanley's Wet Goods",
      "thumbnail": "https://i.ytimg.com/vi/QsDoyCBHub0/mqdefault.jpg",
      "publishedAt": "2026-07-01T01:01:37Z",
      "categories": [
        "Winemaking & Viticulture"
      ],
      "regions": [],
      "beverageType": "wine"
    },
    {
      "videoId": "tjFr2_8ZDRI",
      "title": "Tequila: From Sacred Aztec Rituals to Rowdy Cancun Spring Breaks",
      "channel": "The Tipsy Timeline",
      "thumbnail": "https://i.ytimg.com/vi/tjFr2_8ZDRI/mqdefault.jpg",
      "publishedAt": "2026-07-01T01:00:36Z",
      "categories": [
        "Pulque"
      ],
      "regions": [
        "Jalisco"
      ],
      "beverageType": "spirits"
    },
    {
      "videoId": "LPKV00DhFhc",
      "title": "Ranch at Uptown Celina | This Bathroom Feels Like a Spa",
      "channel": "Jake Inderman | Dallas, Frisco and Prosper Living",
      "thumbnail": "https://i.ytimg.com/vi/LPKV00DhFhc/mqdefault.jpg",
      "publishedAt": "2026-07-01T01:00:22Z",
      "categories": [
        "Wine Collecting & Investment"
      ],
      "regions": [],
      "beverageType": "wine"
    },
    {
      "videoId": "SsNribGWllo",
      "title": "Your 4th of July drink just got a creamy upgrade! 🇺🇸🥤",
      "channel": "Carnation Milk",
      "thumbnail": "https://i.ytimg.com/vi/SsNribGWllo/mqdefault.jpg",
      "publishedAt": "2026-07-01T01:00:20Z",
      "categories": [
        "Cocktails & Mixology"
      ],
      "regions": [],
      "beverageType": "spirits"
    },
    {
      "videoId": "dEwv_RkMIGs",
      "title": "Italian Female POWs in California Were Shocked Cowboys Let Them Make Wine on the Ranch | HISTORY",
      "channel": "Obsidian War Room",
      "thumbnail": "https://i.ytimg.com/vi/dEwv_RkMIGs/mqdefault.jpg",
      "publishedAt": "2026-07-01T00:47:16Z",
      "categories": [
        "Wines by Region"
      ],
      "regions": [],
      "beverageType": "wine"
    },
    {
      "videoId": "D39t5FVTn2k",
      "title": "The 2021 Markham Merlot from Napa Valley with Sommelier David LeClaire",
      "channel": "Wine Guy",
      "thumbnail": "https://i.ytimg.com/vi/D39t5FVTn2k/mqdefault.jpg",
      "publishedAt": "2026-07-01T00:38:38Z",
      "categories": [
        "Wines by Region",
        "Grape Varieties"
      ],
      "regions": [
        "California"
      ],
      "beverageType": "wine"
    },
    {
      "videoId": "bU4R5nhJDug",
      "title": "Best Rye Whiskey Deal: Shockingly Fruity &amp; Affordable! #shorts",
      "channel": "MoJo Whiskey Bar",
      "thumbnail": "https://i.ytimg.com/vi/bU4R5nhJDug/mqdefault.jpg",
      "publishedAt": "2026-07-01T00:33:29Z",
      "categories": [
        "Whiskey"
      ],
      "regions": [],
      "beverageType": "spirits"
    },
    {
      "videoId": "1nJ-HeAldLw",
      "title": "🔥*SAVE*🔥make this at your bbq 😋Italian sausage w/peppers &amp; onions is easy + delish *try recipe ⬇️",
      "channel": "Carmen Ortiz",
      "thumbnail": "https://i.ytimg.com/vi/1nJ-HeAldLw/mqdefault.jpg",
      "publishedAt": "2026-07-01T00:27:40Z",
      "categories": [
        "Wines by Region"
      ],
      "regions": [],
      "beverageType": "wine"
    },
    {
      "videoId": "Z8DuoFG-5Vs",
      "title": "13th Colony Flavor in your Ear!!#bourbon #whisky #indiana",
      "channel": "Tha Pour",
      "thumbnail": "https://i.ytimg.com/vi/Z8DuoFG-5Vs/mqdefault.jpg",
      "publishedAt": "2026-07-01T00:24:57Z",
      "categories": [
        "Whiskey"
      ],
      "regions": [
        "Kentucky"
      ],
      "beverageType": "spirits"
    },
    {
      "videoId": "1q9YtAKD5gU",
      "title": "Episode 3 | How I Got Into the Wine Industry 🍷",
      "channel": "Starlyn Fernandez",
      "thumbnail": "https://i.ytimg.com/vi/1q9YtAKD5gU/mqdefault.jpg",
      "publishedAt": "2026-07-01T00:20:29Z",
      "categories": [
        "Business & Trade"
      ],
      "regions": [],
      "beverageType": "wine"
    },
    {
      "videoId": "MOC99VgpF6E",
      "title": "Inside WineaPAWlooza 2026 | Napa&#39;s Premier Animal Fundraiser",
      "channel": "mrcheezypop",
      "thumbnail": "https://i.ytimg.com/vi/MOC99VgpF6E/mqdefault.jpg",
      "publishedAt": "2026-07-01T00:14:08Z",
      "categories": [
        "Wines by Region"
      ],
      "regions": [],
      "beverageType": "wine"
    },
    {
      "videoId": "8B2f3vjNYlo",
      "title": "Bourbon Review: Is Woodford Reserve Wheat Polarizing? #shorts",
      "channel": "Tortured Bourbon",
      "thumbnail": "https://i.ytimg.com/vi/8B2f3vjNYlo/mqdefault.jpg",
      "publishedAt": "2026-07-01T00:03:29Z",
      "categories": [
        "Whiskey"
      ],
      "regions": [
        "Kentucky"
      ],
      "beverageType": "spirits"
    },
    {
      "videoId": "eZ5oTJ6I_5c",
      "title": "Blind review of Creme de Liqueur&#39;s &quot;Chocolate Brownie Bourbon&quot; Ice Cream #tastetest #icecream",
      "channel": "With Love, Kennita ",
      "thumbnail": "https://i.ytimg.com/vi/eZ5oTJ6I_5c/mqdefault.jpg",
      "publishedAt": "2026-07-01T00:00:33Z",
      "categories": [
        "Whiskey"
      ],
      "regions": [
        "Kentucky"
      ],
      "beverageType": "spirits"
    },
    {
      "videoId": "wEZYD_9fpsU",
      "title": "🍍 The frozen summer cocktail you’ll be making on repeat",
      "channel": "Little Bits of Real Food",
      "thumbnail": "https://i.ytimg.com/vi/wEZYD_9fpsU/mqdefault.jpg",
      "publishedAt": "2026-06-30T23:59:23Z",
      "categories": [
        "Cocktails & Mixology"
      ],
      "regions": [],
      "beverageType": "spirits"
    },
    {
      "videoId": "PHlV2tourW4",
      "title": "Homemade Jamson Wine 🍷 #viralvideo #cooking #viral #foodie #food #wine #homemade #dc #winetricks",
      "channel": "Don's Hub",
      "thumbnail": "https://i.ytimg.com/vi/PHlV2tourW4/mqdefault.jpg",
      "publishedAt": "2026-06-30T23:41:46Z",
      "categories": [
        "Wine & Food"
      ],
      "regions": [],
      "beverageType": "wine"
    },
    {
      "videoId": "f5_lNLZpkz0",
      "title": "Advice From Previous Wine Business Owner",
      "channel": "Winners Win",
      "thumbnail": "https://i.ytimg.com/vi/f5_lNLZpkz0/mqdefault.jpg",
      "publishedAt": "2026-06-30T23:40:28Z",
      "categories": [
        "Business & Trade"
      ],
      "regions": [],
      "beverageType": "wine"
    },
    {
      "videoId": "7soWLt073QI",
      "title": "Juggling taste , give it a try #winemaking #homemadewine #naturalwine",
      "channel": "JennyB",
      "thumbnail": "https://i.ytimg.com/vi/7soWLt073QI/mqdefault.jpg",
      "publishedAt": "2026-06-30T23:31:59Z",
      "categories": [
        "Winemaking & Viticulture"
      ],
      "regions": [],
      "beverageType": "wine"
    },
    {
      "videoId": "kBN51wi6f8s",
      "title": "How Joey Pedone Turned Industry Relationships Into Two Successful Businesses",
      "channel": "Pour Decisions Podcast",
      "thumbnail": "https://i.ytimg.com/vi/kBN51wi6f8s/mqdefault.jpg",
      "publishedAt": "2026-06-30T23:30:49Z",
      "categories": [
        "Spirits Business"
      ],
      "regions": [],
      "beverageType": "spirits"
    },
    {
      "videoId": "8CS-206-XYw",
      "title": "Little Bird Fashioned | Our Signature Take on an Old Fashioned",
      "channel": "Little Bird Fairhope",
      "thumbnail": "https://i.ytimg.com/vi/8CS-206-XYw/mqdefault.jpg",
      "publishedAt": "2026-06-30T23:30:35Z",
      "categories": [
        "Cocktails & Mixology"
      ],
      "regions": [],
      "beverageType": "spirits"
    },
    {
      "videoId": "pIleAZkFIaY",
      "title": "27 Years of Abandonment. One Man Who Saw Something Nobody Else Did. | Castle & Key | Whiskey Library",
      "channel": "Whiskey Library",
      "thumbnail": "https://i.ytimg.com/vi/pIleAZkFIaY/mqdefault.jpg",
      "publishedAt": "2026-06-30T23:30:06.000Z",
      "categories": [
        "Distilleries"
      ],
      "regions": [],
      "beverageType": "spirits"
    },
    {
      "videoId": "Uo0-Pw2jSAQ",
      "title": "The Ultimate Juneteenth Cookout! 🇺🇸🥩 + Black-Owned Tequila Taste Test",
      "channel": "Sip and sizzle",
      "thumbnail": "https://i.ytimg.com/vi/Uo0-Pw2jSAQ/mqdefault.jpg",
      "publishedAt": "2026-06-30T23:30:00Z",
      "categories": [
        "Tequila & Mezcal"
      ],
      "regions": [
        "Jalisco"
      ],
      "beverageType": "spirits"
    },
    {
      "videoId": "g6oapqE8QyA",
      "title": "D&#39;armagnac 👑",
      "channel": "Fortifiant07 ",
      "thumbnail": "https://i.ytimg.com/vi/g6oapqE8QyA/mqdefault.jpg",
      "publishedAt": "2026-06-30T23:28:27Z",
      "categories": [
        "Brandy & Cognac"
      ],
      "regions": [
        "France"
      ],
      "beverageType": "spirits"
    },
    {
      "videoId": "1O0BONor730",
      "title": "Dana Point Wine Festival Part 3 | California Wine Tastings &amp; Festival Highlights",
      "channel": "Wine Guardian Dealer",
      "thumbnail": "https://i.ytimg.com/vi/1O0BONor730/mqdefault.jpg",
      "publishedAt": "2026-06-30T23:14:52Z",
      "categories": [
        "Wine Collecting & Investment"
      ],
      "regions": [
        "California"
      ],
      "beverageType": "wine"
    },
    {
      "videoId": "VTScPkvPxW0",
      "title": "Tasting 50 Moonshines &amp; Whiskeys: An Unforgettable Afternoon! #shorts",
      "channel": "Whiskey Witches",
      "thumbnail": "https://i.ytimg.com/vi/VTScPkvPxW0/mqdefault.jpg",
      "publishedAt": "2026-06-30T23:14:19Z",
      "categories": [
        "Whiskey"
      ],
      "regions": [],
      "beverageType": "spirits"
    },
    {
      "videoId": "ZUwiQBkStps",
      "title": "Star Hill Farm 2026 American Wheat Whiskey Review",
      "channel": "The Mash and Drum",
      "thumbnail": "https://i.ytimg.com/vi/ZUwiQBkStps/mqdefault.jpg",
      "publishedAt": "2026-06-30T23:08:08Z",
      "categories": [
        "Whiskey"
      ],
      "regions": [],
      "beverageType": "spirits"
    },
    {
      "videoId": "0-Imqtthocc",
      "title": "#creatorsearchinsights #نص_إلى_كلام French&#39;s  wine 3_0 swidوتتاهل لدوري16#FIFA #soccer #WorldCup",
      "channel": "YASSER GANDOWER",
      "thumbnail": "https://i.ytimg.com/vi/0-Imqtthocc/mqdefault.jpg",
      "publishedAt": "2026-06-30T23:06:40Z",
      "categories": [
        "Wines by Region"
      ],
      "regions": [],
      "beverageType": "wine"
    },
    {
      "videoId": "YfQ_-97DFPc",
      "title": "Dana Point Wine Festival Part 2 | More California Wine Tastings &amp; Festival Highlights",
      "channel": "Wine Guardian Dealer",
      "thumbnail": "https://i.ytimg.com/vi/YfQ_-97DFPc/mqdefault.jpg",
      "publishedAt": "2026-06-30T23:03:59Z",
      "categories": [
        "Wine Collecting & Investment"
      ],
      "regions": [
        "California"
      ],
      "beverageType": "wine"
    },
    {
      "videoId": "0hDI8VmJohQ",
      "title": "POV: Talisker Old Fashioned Twist 🥃🔥",
      "channel": "ChrisTender",
      "thumbnail": "https://i.ytimg.com/vi/0hDI8VmJohQ/mqdefault.jpg",
      "publishedAt": "2026-06-30T23:00:59Z",
      "categories": [
        "Cocktails & Mixology"
      ],
      "regions": [
        "Scotland"
      ],
      "beverageType": "spirits"
    },
    {
      "videoId": "plTikdJzhVw",
      "title": "A Day at B58 Winery: Vineyard Tasting &amp; Summer Sartorial Elegance",
      "channel": "big gentleman  little lady",
      "thumbnail": "https://i.ytimg.com/vi/plTikdJzhVw/mqdefault.jpg",
      "publishedAt": "2026-06-30T23:00:28Z",
      "categories": [
        "Wineries"
      ],
      "regions": [],
      "beverageType": "wine"
    },
    {
      "videoId": "XvI1LfhKmdU",
      "title": "Your Wine Tastes Horrible Because of This",
      "channel": "The Great Bite",
      "thumbnail": "https://i.ytimg.com/vi/XvI1LfhKmdU/mqdefault.jpg",
      "publishedAt": "2026-06-30T23:00:15Z",
      "categories": [
        "Tasting & Sommelier"
      ],
      "regions": [],
      "beverageType": "wine"
    },
    {
      "videoId": "REdyhOSd4J0",
      "title": "BASTIDORES DO VINHO - EP. 1: A PROPOSTA - PROF. MARCELO VARGAS E CRISTIAN SILVA",
      "channel": "Marcelo Vargas",
      "thumbnail": "https://i.ytimg.com/vi/REdyhOSd4J0/mqdefault.jpg",
      "publishedAt": "2026-06-30T23:00:06Z",
      "categories": [
        "Winemaking & Viticulture"
      ],
      "regions": [],
      "beverageType": "wine"
    },
    {
      "videoId": "rfnoj4sgk34",
      "title": "Whiskey Awards mean Nothing!?!? #awards #whiskey #wow #unbelievable #contest",
      "channel": "T-Rod Whiskey",
      "thumbnail": "https://i.ytimg.com/vi/rfnoj4sgk34/mqdefault.jpg",
      "publishedAt": "2026-06-30T22:59:22Z",
      "categories": [
        "Whiskey"
      ],
      "regions": [],
      "beverageType": "spirits"
    },
    {
      "videoId": "MDqMKQlCD7M",
      "title": "I call it &quot;Whiskey Roulette&quot; how will my whiskey taste today?",
      "channel": "Bourbon Of The Week",
      "thumbnail": "https://i.ytimg.com/vi/MDqMKQlCD7M/mqdefault.jpg",
      "publishedAt": "2026-06-30T22:55:28Z",
      "categories": [
        "Whiskey"
      ],
      "regions": [
        "Kentucky"
      ],
      "beverageType": "spirits"
    },
    {
      "videoId": "OMKf_KUSqIk",
      "title": "Bardolino, Italy 🇮🇹 Lake Garda Wine Festival | 360° VR Walking Tour | Palio del Chiaretto",
      "channel": "ProwalkTours 360",
      "thumbnail": "https://i.ytimg.com/vi/OMKf_KUSqIk/mqdefault.jpg",
      "publishedAt": "2026-06-30T22:52:10Z",
      "categories": [
        "Wineries"
      ],
      "regions": [],
      "beverageType": "wine"
    },
    {
      "videoId": "Q6_ttLbQVVc",
      "title": "Dana Point Wine Festival Part 1 | Discover California&#39;s Premier Wine Tasting Event",
      "channel": "Wine Guardian Dealer",
      "thumbnail": "https://i.ytimg.com/vi/Q6_ttLbQVVc/mqdefault.jpg",
      "publishedAt": "2026-06-30T22:51:52Z",
      "categories": [
        "Business & Trade",
        "Wineries"
      ],
      "regions": [],
      "beverageType": "wine"
    },
    {
      "videoId": "WzW4E0zYtPE",
      "title": "Oral History Interview with Jenny Burger",
      "channel": "Linfield Archives",
      "thumbnail": "https://i.ytimg.com/vi/WzW4E0zYtPE/mqdefault.jpg",
      "publishedAt": "2026-06-30T22:50:55Z",
      "categories": [
        "Business & Trade"
      ],
      "regions": [],
      "beverageType": "wine"
    },
    {
      "videoId": "0j3EHNxhgJk",
      "title": "Best White Wines for Long-Term Aging | Top Age-Worthy White Wines Explained",
      "channel": "Wine Guardian Dealer",
      "thumbnail": "https://i.ytimg.com/vi/0j3EHNxhgJk/mqdefault.jpg",
      "publishedAt": "2026-06-30T22:39:14Z",
      "categories": [
        "Business & Trade",
        "Grape Varieties"
      ],
      "regions": [],
      "beverageType": "wine"
    },
    {
      "videoId": "HHf4EBICCz4",
      "title": "Portugal Day 5: Coimbra, Bairrada Sparkling Wine &amp; a Wilderness Cooking Class",
      "channel": "Vineyard Voyages",
      "thumbnail": "https://i.ytimg.com/vi/HHf4EBICCz4/mqdefault.jpg",
      "publishedAt": "2026-06-30T22:30:38Z",
      "categories": [
        "Wine & Food"
      ],
      "regions": [],
      "beverageType": "wine"
    },
    {
      "videoId": "nUQehsLJd6E",
      "title": "A beautiful Chinese model wearing a wine-red leather skirt at the outdoor area of Guangzhou Show",
      "channel": "Oriental Fashion",
      "thumbnail": "https://i.ytimg.com/vi/nUQehsLJd6E/mqdefault.jpg",
      "publishedAt": "2026-06-30T22:30:31Z",
      "categories": [
        "Emerging Wine Regions"
      ],
      "regions": [],
      "beverageType": "wine"
    },
    {
      "videoId": "8Ghh0-shjO4",
      "title": "Di Fara Vodka Sauce Pizza Review Part 4b #pizza #foodreview #eating #frozenpizza",
      "channel": "AVigEats",
      "thumbnail": "https://i.ytimg.com/vi/8Ghh0-shjO4/mqdefault.jpg",
      "publishedAt": "2026-06-30T22:30:27Z",
      "categories": [
        "Vodka"
      ],
      "regions": [],
      "beverageType": "spirits"
    },
    {
      "videoId": "8t67NynVsnM",
      "title": "Quick and easy white wine-garlic butter sauce  #cooking #food #tips",
      "channel": "Chef Nathan Buckley",
      "thumbnail": "https://i.ytimg.com/vi/8t67NynVsnM/mqdefault.jpg",
      "publishedAt": "2026-06-30T22:25:15Z",
      "categories": [
        "Wine & Food"
      ],
      "regions": [],
      "beverageType": "wine"
    },
    {
      "videoId": "ENYgMU8Dus4",
      "title": "Disrupting Wine: From Artificial Intelligence to Winning Orange Wines in Armenia. Luiza Avetisyan",
      "channel": "Wine Talks with Paul K",
      "thumbnail": "https://i.ytimg.com/vi/ENYgMU8Dus4/mqdefault.jpg",
      "publishedAt": "2026-06-30T22:19:56Z",
      "categories": [
        "Business & Trade"
      ],
      "regions": [],
      "beverageType": "wine"
    },
    {
      "videoId": "eqHm2bn_gKc",
      "title": "The Muscat Czech Winemakers Invented | Muškát Moravský",
      "channel": "Uncorkmywine | Jan Eggers",
      "thumbnail": "https://i.ytimg.com/vi/eqHm2bn_gKc/mqdefault.jpg",
      "publishedAt": "2026-06-30T22:19:35Z",
      "categories": [
        "Wine Education"
      ],
      "regions": [],
      "beverageType": "wine"
    },
    {
      "videoId": "_FmbCpUlG5M",
      "title": "Texas Vodka Uncorked: From Local Roots to Global Flavor | Let&#39;s Wine A Little",
      "channel": "G R Houston-Jack",
      "thumbnail": "https://i.ytimg.com/vi/_FmbCpUlG5M/mqdefault.jpg",
      "publishedAt": "2026-06-30T22:15:05Z",
      "categories": [
        "Vodka"
      ],
      "regions": [],
      "beverageType": "spirits"
    },
    {
      "videoId": "DVU8ZX9bPDs",
      "title": "2021 - Rombauer - Cabernet Sauvignon/Blend",
      "channel": "Time for Wine and More",
      "thumbnail": "https://i.ytimg.com/vi/DVU8ZX9bPDs/mqdefault.jpg",
      "publishedAt": "2026-06-30T22:08:24Z",
      "categories": [
        "Grape Varieties"
      ],
      "regions": [],
      "beverageType": "wine"
    },
    {
      "videoId": "Rql2qD8MA4Y",
      "title": "Celebrating National Rosé Day with Marc Supsic | Wine Guardian Wine Tasting",
      "channel": "Wine Guardian Dealer",
      "thumbnail": "https://i.ytimg.com/vi/Rql2qD8MA4Y/mqdefault.jpg",
      "publishedAt": "2026-06-30T22:06:24Z",
      "categories": [
        "Tasting & Sommelier"
      ],
      "regions": [],
      "beverageType": "wine"
    },
    {
      "videoId": "ygQsoHiT7Gg",
      "title": "Craft a cocktail today with Drinkstir #cocktail #drinkrecipe #cocktailrecipe #bartender #mixology",
      "channel": "Drinkstir App",
      "thumbnail": "https://i.ytimg.com/vi/ygQsoHiT7Gg/mqdefault.jpg",
      "publishedAt": "2026-06-30T22:03:27.000Z",
      "categories": [
        "Cocktails & Mixology"
      ],
      "regions": [],
      "beverageType": "spirits"
    },
    {
      "videoId": "f73OIqAxwdc",
      "title": "¿Sabes realmente qué hay detrás de tu vino orgánico?",
      "channel": "Wineglups",
      "thumbnail": "https://i.ytimg.com/vi/f73OIqAxwdc/mqdefault.jpg",
      "publishedAt": "2026-06-30T22:01:41Z",
      "categories": [
        "Sustainability & Climate"
      ],
      "regions": [],
      "beverageType": "wine"
    },
    {
      "videoId": "uR_iKwEr6ro",
      "title": "Lo Chardonnay dell&#39;Alto Adige in degustazione alla cieca | Guida Untold 2027",
      "channel": "Decanto - Your Wine Advisor",
      "thumbnail": "https://i.ytimg.com/vi/uR_iKwEr6ro/mqdefault.jpg",
      "publishedAt": "2026-06-30T22:00:36Z",
      "categories": [
        "Grape Varieties"
      ],
      "regions": [],
      "beverageType": "wine"
    },
    {
      "videoId": "lAHS9wNV2Yo",
      "title": "Mendoza, Argentina’s premier wine region, offers hundreds of vineyards.",
      "channel": "VIP Journeys - South America Tours",
      "thumbnail": "https://i.ytimg.com/vi/lAHS9wNV2Yo/mqdefault.jpg",
      "publishedAt": "2026-06-30T22:00:32Z",
      "categories": [
        "Wineries"
      ],
      "regions": [
        "Argentina"
      ],
      "beverageType": "wine"
    },
    {
      "videoId": "5CZEnDubcfc",
      "title": "Peter Michael Winery: How a British Knight Built a California Dynasty",
      "channel": "The Wine Centric Show",
      "thumbnail": "https://i.ytimg.com/vi/5CZEnDubcfc/mqdefault.jpg",
      "publishedAt": "2026-06-30T22:00:05Z",
      "categories": [
        "Wines by Region",
        "Grape Varieties"
      ],
      "regions": [],
      "beverageType": "wine"
    },
    {
      "videoId": "uWON14ColXA",
      "title": "The Best Night of Monticello Wine Week 🍷🏆 Virginia Wine at Its Finest!",
      "channel": "CurlyQ Family Adventures",
      "thumbnail": "https://i.ytimg.com/vi/uWON14ColXA/mqdefault.jpg",
      "publishedAt": "2026-06-30T21:54:02Z",
      "categories": [
        "Wineries"
      ],
      "regions": [
        "Virginia"
      ],
      "beverageType": "wine"
    },
    {
      "videoId": "ZfG7XGbQsdo",
      "title": "Support the Nonino distillery!! #amaro #amarononino #drinkinitin",
      "channel": "DrinkinItIn",
      "thumbnail": "https://i.ytimg.com/vi/ZfG7XGbQsdo/mqdefault.jpg",
      "publishedAt": "2026-06-30T21:48:45Z",
      "categories": [
        "Business & Trade"
      ],
      "regions": [
        "Italy"
      ],
      "beverageType": "wine"
    },
    {
      "videoId": "NT-FHNIktns",
      "title": "Let’s Revisit Amador Whiskey Company Straight Rye finished in Port barrels.",
      "channel": "Whiskey Phoenix",
      "thumbnail": "https://i.ytimg.com/vi/NT-FHNIktns/mqdefault.jpg",
      "publishedAt": "2026-06-30T21:44:29Z",
      "categories": [
        "Whiskey"
      ],
      "regions": [],
      "beverageType": "spirits"
    },
    {
      "videoId": "2k5N3cP2WM4",
      "title": "The Wisdom of Wine: Terroir, Soil Health &amp; Biodynamic Farming in France pt.1",
      "channel": "Harvesting Wisdom with Mike McMahon",
      "thumbnail": "https://i.ytimg.com/vi/2k5N3cP2WM4/mqdefault.jpg",
      "publishedAt": "2026-06-30T21:39:25Z",
      "categories": [
        "Sustainability & Climate"
      ],
      "regions": [
        "France"
      ],
      "beverageType": "wine"
    },
    {
      "videoId": "kZaQ-Se221w",
      "title": "checking in on the wine grapes #biodynamicwine #biodynamic",
      "channel": "Michael Martin",
      "thumbnail": "https://i.ytimg.com/vi/kZaQ-Se221w/mqdefault.jpg",
      "publishedAt": "2026-06-30T21:38:19Z",
      "categories": [
        "Sustainability & Climate"
      ],
      "regions": [],
      "beverageType": "wine"
    },
    {
      "videoId": "a15aiNW6uk0",
      "title": "What a Day Wine Touring Kelowna Can Look Like 🥂| Kelowna Wine Tours | Vivid Tours",
      "channel": "Vivid Tours",
      "thumbnail": "https://i.ytimg.com/vi/a15aiNW6uk0/mqdefault.jpg",
      "publishedAt": "2026-06-30T21:34:52Z",
      "categories": [
        "Wineries"
      ],
      "regions": [],
      "beverageType": "wine"
    },
    {
      "videoId": "aAbZmab4oF8",
      "title": "2010 Spring Mountain Estate Cabernet Sauvignon from Napa Valley with Sommelier David LeClaire",
      "channel": "Wine Guy",
      "thumbnail": "https://i.ytimg.com/vi/aAbZmab4oF8/mqdefault.jpg",
      "publishedAt": "2026-06-30T21:33:47Z",
      "categories": [
        "Wines by Region",
        "Grape Varieties"
      ],
      "regions": [
        "California"
      ],
      "beverageType": "wine"
    },
    {
      "videoId": "VOnMs0oCK1E",
      "title": "Chateau Laffitte Carcasset T3 Cabernet Sauvignon 2022: Fresh Acidity, Fine Structure and Toasty Oak",
      "channel": "David Allen - Master of Wine",
      "thumbnail": "https://i.ytimg.com/vi/VOnMs0oCK1E/mqdefault.jpg",
      "publishedAt": "2026-06-30T21:30:04Z",
      "categories": [
        "Grape Varieties"
      ],
      "regions": [],
      "beverageType": "wine"
    },
    {
      "videoId": "729jyQgDYEY",
      "title": "☕ The Great Coffee Debate: Starbucks Caramel Macchiato Regular vs. Zero Creamer",
      "channel": "Brandy and Jack's Excellent Reviews",
      "thumbnail": "https://i.ytimg.com/vi/729jyQgDYEY/mqdefault.jpg",
      "publishedAt": "2026-06-30T21:24:30Z",
      "categories": [
        "Brandy & Cognac"
      ],
      "regions": [],
      "beverageType": "spirits"
    },
    {
      "videoId": "8S1S7ELcW98",
      "title": "Feel like royalty at Castello Di Amorosa | Cody&#39;s Caravan",
      "channel": "Good Day Sacramento",
      "thumbnail": "https://i.ytimg.com/vi/8S1S7ELcW98/mqdefault.jpg",
      "publishedAt": "2026-06-30T21:21:05Z",
      "categories": [
        "Wines by Region"
      ],
      "regions": [],
      "beverageType": "wine"
    },
    {
      "videoId": "zsCTeC18bXE",
      "title": "What a Day of Wine Touring in Kelowna with Vivid Tours Looks Like 🍷 | Kelowna Wine Tours",
      "channel": "Vivid Tours",
      "thumbnail": "https://i.ytimg.com/vi/zsCTeC18bXE/mqdefault.jpg",
      "publishedAt": "2026-06-30T21:20:06Z",
      "categories": [
        "Wineries"
      ],
      "regions": [],
      "beverageType": "wine"
    },
    {
      "videoId": "p-d8VFm3r8M",
      "title": "Speed Brake Armed live at Bodegas Papiamento Distillery in Aruba. Pinch me! Is this real?? #aruba",
      "channel": "Speed Brake Armed",
      "thumbnail": "https://i.ytimg.com/vi/p-d8VFm3r8M/mqdefault.jpg",
      "publishedAt": "2026-06-30T21:18:27Z",
      "categories": [
        "Distilleries"
      ],
      "regions": [],
      "beverageType": "spirits"
    },
    {
      "videoId": "SKWMRBXw7WA",
      "title": "Jack Daniel Distillery Tour",
      "channel": "Cask & Char",
      "thumbnail": "https://i.ytimg.com/vi/SKWMRBXw7WA/mqdefault.jpg",
      "publishedAt": "2026-06-30T21:14:57Z",
      "categories": [
        "Distilleries"
      ],
      "regions": [
        "Tennessee"
      ],
      "beverageType": "spirits"
    },
    {
      "videoId": "QCaN0klv3ew",
      "title": "This Chicago Cocktail Class Was a Whole Vibe 🔥",
      "channel": "Let's Go Esco!",
      "thumbnail": "https://i.ytimg.com/vi/QCaN0klv3ew/mqdefault.jpg",
      "publishedAt": "2026-06-30T21:11:50Z",
      "categories": [
        "Cocktails & Mixology"
      ],
      "regions": [],
      "beverageType": "spirits"
    },
    {
      "videoId": "JKiDCyk_aFM",
      "title": "Envelhecer! ww.rocadegarca.com.br",
      "channel": "Cachaça Roça de Garça ",
      "thumbnail": "https://i.ytimg.com/vi/JKiDCyk_aFM/mqdefault.jpg",
      "publishedAt": "2026-06-30T21:10:29Z",
      "categories": [
        "Cachaça"
      ],
      "regions": [
        "Brazil"
      ],
      "beverageType": "spirits"
    },
    {
      "videoId": "YAEaKdPdns8",
      "title": "The Fine Grapes Behind Premium US Wine! #Shorts",
      "channel": "The Factory Insider",
      "thumbnail": "https://i.ytimg.com/vi/YAEaKdPdns8/mqdefault.jpg",
      "publishedAt": "2026-06-30T21:03:22Z",
      "categories": [
        "Wines by Region"
      ],
      "regions": [],
      "beverageType": "wine"
    },
    {
      "videoId": "6B7B_Lh89n4",
      "title": "The ultimate girl dinner! Cheese, charcuterie, crackers and wine (and grilled cheese) Shaver Hall",
      "channel": "Chewyorkcity",
      "thumbnail": "https://i.ytimg.com/vi/6B7B_Lh89n4/mqdefault.jpg",
      "publishedAt": "2026-06-30T21:02:39Z",
      "categories": [
        "Wine & Food"
      ],
      "regions": [],
      "beverageType": "wine"
    },
    {
      "videoId": "rKSXrdlp5BM",
      "title": "New Science: Fermentation + Fruit = Wine",
      "channel": "New Science",
      "thumbnail": "https://i.ytimg.com/vi/rKSXrdlp5BM/mqdefault.jpg",
      "publishedAt": "2026-06-30T21:01:22Z",
      "categories": [
        "Winemaking & Viticulture"
      ],
      "regions": [],
      "beverageType": "wine"
    },
    {
      "videoId": "S-YwKymNWZU",
      "title": "The wine industry is broken",
      "channel": "unPINNED",
      "thumbnail": "https://i.ytimg.com/vi/S-YwKymNWZU/mqdefault.jpg",
      "publishedAt": "2026-06-30T21:00:42Z",
      "categories": [
        "Business & Trade"
      ],
      "regions": [],
      "beverageType": "wine"
    },
    {
      "videoId": "st34A46gZBs",
      "title": "Secret in Great-Grandfather’s Wine Gourd — Chinese Reading and Listening Practice",
      "channel": "Du Chinese",
      "thumbnail": "https://i.ytimg.com/vi/st34A46gZBs/mqdefault.jpg",
      "publishedAt": "2026-06-30T21:00:10Z",
      "categories": [
        "Emerging Wine Regions"
      ],
      "regions": [],
      "beverageType": "wine"
    },
    {
      "videoId": "xETWwEjs1E0",
      "title": "Clos du Bois: Game Winning Chardonnay",
      "channel": "Clos du Bois Wines",
      "thumbnail": "https://i.ytimg.com/vi/xETWwEjs1E0/mqdefault.jpg",
      "publishedAt": "2026-06-30T20:58:39Z",
      "categories": [
        "Grape Varieties"
      ],
      "regions": [],
      "beverageType": "wine"
    },
    {
      "videoId": "3g04ClxD90Q",
      "title": "French Deep House 2026 | Burgundy Cellar Tasting Sessions 🍾",
      "channel": "French Deep House",
      "thumbnail": "https://i.ytimg.com/vi/3g04ClxD90Q/mqdefault.jpg",
      "publishedAt": "2026-06-30T20:51:40Z",
      "categories": [
        "Wines by Region"
      ],
      "regions": [
        "France"
      ],
      "beverageType": "wine"
    },
    {
      "videoId": "ied5hRvh10c",
      "title": "Trying Pennsylvania Wines with Marc Supsic | Wine Living",
      "channel": "Wine Guardian Dealer",
      "thumbnail": "https://i.ytimg.com/vi/ied5hRvh10c/mqdefault.jpg",
      "publishedAt": "2026-06-30T20:48:20Z",
      "categories": [
        "Wineries"
      ],
      "regions": [],
      "beverageType": "wine"
    },
    {
      "videoId": "6YxrZyQKi4Y",
      "title": "The best end of a day #wine #cheese",
      "channel": "Angry dad Life",
      "thumbnail": "https://i.ytimg.com/vi/6YxrZyQKi4Y/mqdefault.jpg",
      "publishedAt": "2026-06-30T20:32:01Z",
      "categories": [
        "Wine & Food"
      ],
      "regions": [],
      "beverageType": "wine"
    },
    {
      "videoId": "x1gPb90lRlo",
      "title": "Napa Valley Wine Train. Afternoon Tea x Chandon",
      "channel": "Here We Go!",
      "thumbnail": "https://i.ytimg.com/vi/x1gPb90lRlo/mqdefault.jpg",
      "publishedAt": "2026-06-30T20:31:03Z",
      "categories": [
        "Wines by Region"
      ],
      "regions": [
        "California"
      ],
      "beverageType": "wine"
    },
    {
      "videoId": "XLy2bZ1RmiE",
      "title": "Penfolds Redemption Episode | Penfolds Max&#39;s Cabernet Sauvignon 2022 Review",
      "channel": "Stop Wasting Your Wine",
      "thumbnail": "https://i.ytimg.com/vi/XLy2bZ1RmiE/mqdefault.jpg",
      "publishedAt": "2026-06-30T20:30:33Z",
      "categories": [
        "Grape Varieties"
      ],
      "regions": [],
      "beverageType": "wine"
    },
    {
      "videoId": "8QSXFMtYTLg",
      "title": "Di Fara Vodka Sauce Pizza Review Part 3b #pizza #foodreview #eating #frozenpizza",
      "channel": "AVigEats",
      "thumbnail": "https://i.ytimg.com/vi/8QSXFMtYTLg/mqdefault.jpg",
      "publishedAt": "2026-06-30T20:15:17Z",
      "categories": [
        "Vodka"
      ],
      "regions": [],
      "beverageType": "spirits"
    },
    {
      "videoId": "2tZTXQaZ26s",
      "title": "The only thing easier than making this cocktail is enjoying it with your toes in the sand. 🍒",
      "channel": "Barritt's Mixers",
      "thumbnail": "https://i.ytimg.com/vi/2tZTXQaZ26s/mqdefault.jpg",
      "publishedAt": "2026-06-30T20:12:51Z",
      "categories": [
        "Cocktails & Mixology"
      ],
      "regions": [],
      "beverageType": "spirits"
    },
    {
      "videoId": "CGxQqK5585c",
      "title": "Love it here #vinyard #napavalley #napa #cali #wine",
      "channel": "Nya",
      "thumbnail": "https://i.ytimg.com/vi/CGxQqK5585c/mqdefault.jpg",
      "publishedAt": "2026-06-30T20:09:45Z",
      "categories": [
        "Wines by Region"
      ],
      "regions": [
        "California"
      ],
      "beverageType": "wine"
    },
    {
      "videoId": "Pp-y_itCf0o",
      "title": "Growing a Wine &amp; Cider Culture - Autumn Stoscheck",
      "channel": "Beyond Organic Wine",
      "thumbnail": "https://i.ytimg.com/vi/Pp-y_itCf0o/mqdefault.jpg",
      "publishedAt": "2026-06-30T20:01:47Z",
      "categories": [
        "Sustainability & Climate"
      ],
      "regions": [],
      "beverageType": "wine"
    }
  ]
}